argvlib/__init__.py
argvlib-1.0.1.dist-info/METADATA
argvlib-1.0.1.dist-info/WHEEL
argvlib-1.0.1.dist-info/top_level.txt
argvlib-1.0.1.dist-info/RECORD
