Metadata-Version: 2.1
Name: argvlib
Version: 1.0.1
Summary: 分析来自命令行的参数,Analyzing parameters from the command line
Home-page: UNKNOWN
Author: Wei Bo 韦博
Author-email: weibo19801379165@yeah.net
License: UNKNOWN
Platform: UNKNOWN
